html_to_jira/__init__.py
html_to_jira/converter.py
html_to_jira-0.1.4.dist-info/LICENSE
html_to_jira-0.1.4.dist-info/METADATA
html_to_jira-0.1.4.dist-info/WHEEL
html_to_jira-0.1.4.dist-info/entry_points.txt
html_to_jira-0.1.4.dist-info/top_level.txt
html_to_jira-0.1.4.dist-info/RECORD
