Metadata-Version: 2.1
Name: html-to-jira
Version: 0.1.4
Summary: A package to convert HTML to Jira Wiki Markup
Home-page: https://github.com/mrsdz/html-to-jira
Author: MohammadReza SDZ
Author-email: org.m.sdz@gmail.com
License: UNKNOWN
Platform: UNKNOWN
Classifier: Programming Language :: Python :: 3
Classifier: License :: OSI Approved :: MIT License
Classifier: Operating System :: OS Independent
License-File: LICENSE
Requires-Dist: beautifulsoup4
